core_evals/mtbench/__init__.py
core_evals/mtbench/framework.yml
core_evals/mtbench/framework_entrypoint.py
core_evals/mtbench/output.py
mtbench_evaluator/__init__.py
mtbench_evaluator/entrypoint.py
mtbench_evaluator/fastchat/Dockerfile_llm_bench
mtbench_evaluator/fastchat/LICENSE
mtbench_evaluator/fastchat/README.md
mtbench_evaluator/fastchat/format.sh
mtbench_evaluator/fastchat/pyproject.toml
mtbench_evaluator/fastchat/assets/qa_browser.png
mtbench_evaluator/fastchat/assets/screenshot_cli.png
mtbench_evaluator/fastchat/assets/screenshot_gui.png
mtbench_evaluator/fastchat/assets/server_arch.png
mtbench_evaluator/fastchat/assets/vicuna_logo.jpeg
mtbench_evaluator/fastchat/data/dummy_conversation.json
mtbench_evaluator/fastchat/docker/Dockerfile
mtbench_evaluator/fastchat/docker/docker-compose.yml
mtbench_evaluator/fastchat/docs/arena.md
mtbench_evaluator/fastchat/docs/awq.md
mtbench_evaluator/fastchat/docs/dataset_release.md
mtbench_evaluator/fastchat/docs/exllama_v2.md
mtbench_evaluator/fastchat/docs/gptq.md
mtbench_evaluator/fastchat/docs/langchain_integration.md
mtbench_evaluator/fastchat/docs/model_support.md
mtbench_evaluator/fastchat/docs/openai_api.md
mtbench_evaluator/fastchat/docs/server_arch.md
mtbench_evaluator/fastchat/docs/training.md
mtbench_evaluator/fastchat/docs/vicuna_weights_version.md
mtbench_evaluator/fastchat/docs/vllm_integration.md
mtbench_evaluator/fastchat/docs/xFasterTransformer.md
mtbench_evaluator/fastchat/docs/commands/conv_release.md
mtbench_evaluator/fastchat/docs/commands/data_cleaning.md
mtbench_evaluator/fastchat/docs/commands/leaderboard.md
mtbench_evaluator/fastchat/docs/commands/local_cluster.md
mtbench_evaluator/fastchat/docs/commands/pypi.md
mtbench_evaluator/fastchat/docs/commands/webserver.md
mtbench_evaluator/fastchat/fastchat/__init__.py
mtbench_evaluator/fastchat/fastchat/constants.py
mtbench_evaluator/fastchat/fastchat/conversation.py
mtbench_evaluator/fastchat/fastchat/utils.py
nvidia_mtbench_evaluator-25.11.dist-info/METADATA
nvidia_mtbench_evaluator-25.11.dist-info/WHEEL
nvidia_mtbench_evaluator-25.11.dist-info/entry_points.txt
nvidia_mtbench_evaluator-25.11.dist-info/top_level.txt
nvidia_mtbench_evaluator-25.11.dist-info/RECORD
