Metadata-Version: 2.4
Name: nvidia_mtbench_evaluator
Version: 25.11
Summary: MTBench evaluator - packaged by NVIDIA
License: Apache
Classifier: Development Status :: 5 - Production/Stable
Classifier: Programming Language :: Python :: 3
Classifier: License :: OSI Approved :: Apache Software License
Classifier: Operating System :: OS Independent
Requires-Python: >=3.10
Requires-Dist: aiohttp
Requires-Dist: fastapi
Requires-Dist: httpx
Requires-Dist: markdown2[all]
Requires-Dist: nh3
Requires-Dist: numpy
Requires-Dist: prompt_toolkit>=3.0.0
Requires-Dist: pydantic<3,>=2.0.0
Requires-Dist: pydantic-settings
Requires-Dist: psutil
Requires-Dist: requests
Requires-Dist: rich>=10.0.0
Requires-Dist: shortuuid
Requires-Dist: tiktoken
Requires-Dist: uvicorn
Requires-Dist: omegaconf==2.4.0.dev3
Requires-Dist: openai>=1.0
Requires-Dist: anthropic>=0.3
Requires-Dist: tenacity
Requires-Dist: accelerate>=0.21
Requires-Dist: peft
Requires-Dist: sentencepiece
Requires-Dist: torch
Requires-Dist: transformers>=4.31.0
Requires-Dist: protobuf
Requires-Dist: ray
Requires-Dist: pandas
Requires-Dist: openpyxl
Requires-Dist: nemo-evaluator
Provides-Extra: webui
Requires-Dist: gradio; extra == "webui"
Provides-Extra: train
Requires-Dist: einops; extra == "train"
Requires-Dist: flash-attn>=2.0; extra == "train"
Requires-Dist: wandb; extra == "train"
Provides-Extra: dev
Requires-Dist: black==23.3.0; extra == "dev"
Requires-Dist: pylint==2.8.2; extra == "dev"
